{"elapsed":"0.166","endpoint-url":"https://raw.githubusercontent.com/digital-land/ancient-woodland-collection/main/data/ancient-woodland-status.csv","entry-date":"2022-10-04T00:20:25.975947","request-headers":{"Accept":"*/*","Accept-Encoding":"gzip, deflate","Connection":"keep-alive","User-Agent":"DLUHC Digital Land"},"resource":"9954b7c5224461b0e522fab787cfc1f1ac1c68088f152374199c3b25587d6347","response-headers":{"Accept-Ranges":"bytes","Access-Control-Allow-Origin":"*","Cache-Control":"max-age=300","Connection":"keep-alive","Content-Encoding":"gzip","Content-Length":"108","Content-Security-Policy":"default-src 'none'; style-src 'unsafe-inline'; sandbox","Content-Type":"text/plain; charset=utf-8","Date":"Tue, 04 Oct 2022 00:20:28 GMT","ETag":"W/\"27b9b776b24073a36cfbb0fd734cdd5960a56ec343ed9d41ef33d18b70a9cfd0\"","Expires":"Tue, 04 Oct 2022 00:25:28 GMT","Source-Age":"0","Strict-Transport-Security":"max-age=31536000","Vary":"Authorization,Accept-Encoding,Origin","Via":"1.1 varnish","X-Cache":"MISS","X-Cache-Hits":"0","X-Content-Type-Options":"nosniff","X-Fastly-Request-ID":"e2cd1ae2df36c4b76b79b87047aaf7fdf517b5a5","X-Frame-Options":"deny","X-GitHub-Request-Id":"0801:9C35:20AAA:495BB:633B7C4B","X-Served-By":"cache-bfi-krnt7300020-BFI","X-Timer":"S1664842828.909781,VS0,VE139","X-XSS-Protection":"1; mode=block"},"ssl-verify":true,"status":"200"}